openbb_nasdaq/__init__.py
openbb_nasdaq/app.py
openbb_nasdaq/models/__init__.py
openbb_nasdaq/models/calendar_dividend.py
openbb_nasdaq/models/calendar_earnings.py
openbb_nasdaq/models/calendar_ipo.py
openbb_nasdaq/models/company_filings.py
openbb_nasdaq/models/economic_calendar.py
openbb_nasdaq/models/equity_screener.py
openbb_nasdaq/models/equity_search.py
openbb_nasdaq/models/historical_dividends.py
openbb_nasdaq/models/top_retail.py
openbb_nasdaq/py.typed
openbb_nasdaq/utils/__init__.py
openbb_nasdaq/utils/helpers.py
openbb_nasdaq/utils/query_params.py
openbb_nasdaq-1.5.1.dist-info/METADATA
openbb_nasdaq-1.5.1.dist-info/WHEEL
openbb_nasdaq-1.5.1.dist-info/entry_points.txt
openbb_nasdaq-1.5.1.dist-info/RECORD
